MANIFEST.in
README.rst
setup.py
src/zc/__init__.py
src/zc.zk.egg-info/PKG-INFO
src/zc.zk.egg-info/SOURCES.txt
src/zc.zk.egg-info/dependency_links.txt
src/zc.zk.egg-info/entry_points.txt
src/zc.zk.egg-info/namespace_packages.txt
src/zc.zk.egg-info/not-zip-safe
src/zc.zk.egg-info/requires.txt
src/zc.zk.egg-info/top_level.txt
src/zc/zk/README.txt
src/zc/zk/__init__.py
src/zc/zk/disconnectiontests.py
src/zc/zk/ephemeral_node_recovery_on_session_reestablishment.test
src/zc/zk/event.py
src/zc/zk/graphvis.py
src/zc/zk/monitor.py
src/zc/zk/monitor.test
src/zc/zk/monitor.zcml
src/zc/zk/scripts.py
src/zc/zk/testing.py
src/zc/zk/tests.py