Metadata-Version: 1.0
Name: zc.zk
Version: 2.1.0
Summary: Service registration and discovery with ZooKeeper
Home-page: UNKNOWN
Author: Jim Fulton
Author-email: jim@zope.com
License: ZPL 2.1
Platform: UNKNOWN
